mm_starknet/__init__.py
mm_starknet/balance.py
mm_starknet/domain.py
mm_starknet/py.typed
mm_starknet/cli/__init__.py
mm_starknet/cli/cli.py
mm_starknet/cli/cli_utils.py
mm_starknet/cli/cmd/__init__.py
mm_starknet/cli/cmd/node_cmd.py
mm_starknet-0.3.0.dist-info/METADATA
mm_starknet-0.3.0.dist-info/WHEEL
mm_starknet-0.3.0.dist-info/entry_points.txt
mm_starknet-0.3.0.dist-info/RECORD
