Metadata-Version: 2.4
Name: mm-starknet
Version: 0.3.0
Requires-Python: >=3.12
Requires-Dist: mm-crypto-utils>=0.3.1
Requires-Dist: starknet-py~=0.26.2
Requires-Dist: typer>=0.15.2
